scanvault/Authentication.py
scanvault/Scan.py
scanvault/__init__.py
scanvault/_config.py
scanvault-0.1.0.dist-info/METADATA
scanvault-0.1.0.dist-info/WHEEL
scanvault-0.1.0.dist-info/top_level.txt
scanvault-0.1.0.dist-info/RECORD
