Metadata-Version: 2.4
Name: scanvault
Version: 0.1.0
Author: Praveenkumar B
License: Owned By Scan Vault
Classifier: Programming Language :: Python :: 3
Classifier: License :: Other/Proprietary License
Classifier: Operating System :: OS Independent
Requires-Python: >=3.6
Dynamic: author
Dynamic: classifier
Dynamic: description
Dynamic: description-content-type
Dynamic: license
Dynamic: requires-python
